[
  {
    "id": "NpcId.MOSS_GIANT_42",
    "direction": 1,
    "moveDistance": 4,
    "x": 2670,
    "y": 9543
  },
  {
    "id": "NpcId.MOSS_GIANT_42",
    "direction": 1,
    "moveDistance": 4,
    "x": 2679,
    "y": 9544
  },
  {
    "id": "NpcId.MOSS_GIANT_42",
    "direction": 1,
    "moveDistance": 4,
    "x": 2676,
    "y": 9550
  },
  {
    "id": "NpcId.MOSS_GIANT_42",
    "direction": 1,
    "moveDistance": 4,
    "x": 2665,
    "y": 9556
  },
  {
    "id": "NpcId.MOSS_GIANT_42",
    "direction": 1,
    "moveDistance": 4,
    "x": 2658,
    "y": 9552
  },
  {
    "id": "NpcId.MOSS_GIANT_42",
    "direction": 1,
    "moveDistance": 4,
    "x": 2656,
    "y": 9546
  },
  {
    "id": "NpcId.MOSS_GIANT_42",
    "direction": 1,
    "moveDistance": 4,
    "x": 2660,
    "y": 9542
  },
  {
    "id": "NpcId.WILD_DOG_63",
    "direction": 1,
    "moveDistance": 4,
    "x": 2679,
    "y": 9562
  },
  {
    "id": "NpcId.MOSS_GIANT_42",
    "direction": 1,
    "moveDistance": 4,
    "x": 2682,
    "y": 9573
  },
  {
    "id": "NpcId.MOSS_GIANT_42",
    "direction": 1,
    "moveDistance": 4,
    "x": 2682,
    "y": 9593
  },
  {
    "id": "NpcId.MOSS_GIANT_42",
    "direction": 1,
    "moveDistance": 4,
    "x": 2673,
    "y": 9590
  },
  {
    "id": "NpcId.MOSS_GIANT_42",
    "direction": 1,
    "moveDistance": 4,
    "x": 2679,
    "y": 9587
  },
  {
    "id": "NpcId.MOSS_GIANT_42",
    "direction": 1,
    "moveDistance": 4,
    "x": 2659,
    "y": 9590
  },
  {
    "id": "NpcId.MOSS_GIANT_42",
    "direction": 1,
    "moveDistance": 4,
    "x": 2653,
    "y": 9586
  },
  {
    "id": "NpcId.MOSS_GIANT_42",
    "direction": 1,
    "moveDistance": 4,
    "x": 2644,
    "y": 9586
  },
  {
    "id": "NpcId.MOSS_GIANT_42",
    "direction": 1,
    "moveDistance": 4,
    "x": 2640,
    "y": 9581
  },
  {
    "id": "NpcId.MOSS_GIANT_42",
    "direction": 1,
    "moveDistance": 4,
    "x": 2642,
    "y": 9574
  },
  {
    "id": "NpcId.MOSS_GIANT_42",
    "direction": 1,
    "moveDistance": 4,
    "x": 2656,
    "y": 9576
  },
  {
    "id": "NpcId.MOSS_GIANT_42",
    "direction": 1,
    "moveDistance": 4,
    "x": 2651,
    "y": 9564
  },
  {
    "id": "NpcId.MOSS_GIANT_42",
    "direction": 1,
    "moveDistance": 4,
    "x": 2647,
    "y": 9552
  },
  {
    "id": "NpcId.MOSS_GIANT_42",
    "direction": 1,
    "moveDistance": 4,
    "x": 2637,
    "y": 9544
  },
  {
    "id": "NpcId.MOSS_GIANT_42",
    "direction": 1,
    "moveDistance": 4,
    "x": 2643,
    "y": 9538
  },
  {
    "id": "NpcId.MOSS_GIANT_42",
    "direction": 1,
    "moveDistance": 4,
    "x": 2651,
    "y": 9536
  },
  {
    "id": "NpcId.MOSS_GIANT_42",
    "direction": 1,
    "moveDistance": 4,
    "x": 2634,
    "y": 9535
  },
  {
    "id": "NpcId.MOSS_GIANT_42",
    "direction": 1,
    "moveDistance": 4,
    "x": 2652,
    "y": 9528
  },
  {
    "id": "NpcId.MOSS_GIANT_42",
    "direction": 1,
    "moveDistance": 4,
    "x": 2646,
    "y": 9531
  },
  {
    "id": "NpcId.MOSS_GIANT_42",
    "direction": 1,
    "moveDistance": 4,
    "x": 2639,
    "y": 9528
  },
  {
    "id": "NpcId.MOSS_GIANT_42",
    "direction": 1,
    "moveDistance": 4,
    "x": 2633,
    "y": 9522
  },
  {
    "id": "NpcId.MOSS_GIANT_42",
    "direction": 1,
    "moveDistance": 4,
    "x": 2642,
    "y": 9520
  },
  {
    "id": "NpcId.WILD_DOG_63",
    "direction": 1,
    "moveDistance": 4,
    "x": 2657,
    "y": 9514
  },
  {
    "id": "NpcId.WILD_DOG_63",
    "direction": 1,
    "moveDistance": 4,
    "x": 2663,
    "y": 9513
  },
  {
    "id": "NpcId.WILD_DOG_63",
    "direction": 1,
    "moveDistance": 4,
    "x": 2666,
    "y": 9512
  },
  {
    "id": "NpcId.WILD_DOG_63",
    "direction": 1,
    "moveDistance": 4,
    "x": 2661,
    "y": 9518
  },
  {
    "id": "NpcId.WILD_DOG_63",
    "direction": 1,
    "moveDistance": 4,
    "x": 2667,
    "y": 9517
  },
  {
    "id": "NpcId.WILD_DOG_63",
    "direction": 1,
    "moveDistance": 4,
    "x": 2672,
    "y": 9515
  },
  {
    "id": "NpcId.WILD_DOG_63",
    "direction": 1,
    "moveDistance": 4,
    "x": 2671,
    "y": 9521
  },
  {
    "id": "NpcId.WILD_DOG_63",
    "direction": 1,
    "moveDistance": 4,
    "x": 2672,
    "y": 9526
  },
  {
    "id": "NpcId.WILD_DOG_63",
    "direction": 1,
    "moveDistance": 4,
    "x": 2664,
    "y": 9520
  },
  {
    "id": "NpcId.WILD_DOG_63",
    "direction": 1,
    "moveDistance": 4,
    "x": 2667,
    "y": 9522
  },
  {
    "id": "NpcId.WILD_DOG_63",
    "direction": 1,
    "moveDistance": 4,
    "x": 2664,
    "y": 9526
  },
  {
    "id": "NpcId.WILD_DOG_63",
    "direction": 1,
    "moveDistance": 4,
    "x": 2660,
    "y": 9522
  },
  {
    "id": "NpcId.GREATER_DEMON_92",
    "direction": 1,
    "moveDistance": 4,
    "x": 2648,
    "y": 9477,
    "height": 2
  },
  {
    "id": "NpcId.GREATER_DEMON_92",
    "direction": 1,
    "moveDistance": 4,
    "x": 2640,
    "y": 9476,
    "height": 2
  },
  {
    "id": "NpcId.GREATER_DEMON_92",
    "direction": 1,
    "moveDistance": 4,
    "x": 2629,
    "y": 9477,
    "height": 2
  },
  {
    "id": "NpcId.GREATER_DEMON_92",
    "direction": 1,
    "moveDistance": 4,
    "x": 2634,
    "y": 9485,
    "height": 2
  },
  {
    "id": "NpcId.GREATER_DEMON_92",
    "direction": 1,
    "moveDistance": 4,
    "x": 2632,
    "y": 9493,
    "height": 2
  },
  {
    "id": "NpcId.GREATER_DEMON_92",
    "direction": 1,
    "moveDistance": 4,
    "x": 2642,
    "y": 9500,
    "height": 2
  },
  {
    "id": "NpcId.GREATER_DEMON_92",
    "direction": 1,
    "moveDistance": 4,
    "x": 2632,
    "y": 9502,
    "height": 2
  },
  {
    "id": "NpcId.GREATER_DEMON_92",
    "direction": 1,
    "moveDistance": 4,
    "x": 2640,
    "y": 9508,
    "height": 2
  },
  {
    "id": "NpcId.GREATER_DEMON_92",
    "direction": 1,
    "moveDistance": 4,
    "x": 2637,
    "y": 9504,
    "height": 2
  },
  {
    "id": "NpcId.GREATER_DEMON_92",
    "direction": 1,
    "moveDistance": 4,
    "x": 2631,
    "y": 9511,
    "height": 2
  },
  {
    "id": "NpcId.WILD_DOG_63",
    "direction": 1,
    "moveDistance": 4,
    "x": 2627,
    "y": 9525,
    "height": 2
  },
  {
    "id": "NpcId.FIRE_GIANT_86",
    "direction": 1,
    "moveDistance": 4,
    "x": 2627,
    "y": 9530,
    "height": 2
  },
  {
    "id": "NpcId.FIRE_GIANT_86",
    "direction": 1,
    "moveDistance": 4,
    "x": 2628,
    "y": 9541,
    "height": 2
  },
  {
    "id": "NpcId.FIRE_GIANT_86",
    "direction": 1,
    "moveDistance": 4,
    "x": 2628,
    "y": 9548,
    "height": 2
  },
  {
    "id": "NpcId.FIRE_GIANT_86",
    "direction": 1,
    "moveDistance": 4,
    "x": 2634,
    "y": 9550,
    "height": 2
  },
  {
    "id": "NpcId.FIRE_GIANT_86",
    "direction": 1,
    "moveDistance": 4,
    "x": 2634,
    "y": 9557,
    "height": 2
  },
  {
    "id": "NpcId.FIRE_GIANT_86",
    "direction": 1,
    "moveDistance": 4,
    "x": 2640,
    "y": 9559,
    "height": 2
  },
  {
    "id": "NpcId.FIRE_GIANT_86",
    "direction": 1,
    "moveDistance": 4,
    "x": 2636,
    "y": 9566,
    "height": 2
  },
  {
    "id": "NpcId.FIRE_GIANT_86",
    "direction": 1,
    "moveDistance": 4,
    "x": 2643,
    "y": 9564,
    "height": 2
  },
  {
    "id": "NpcId.FIRE_GIANT_86",
    "direction": 1,
    "moveDistance": 4,
    "x": 2640,
    "y": 9569,
    "height": 2
  },
  {
    "id": "NpcId.FIRE_GIANT_86",
    "direction": 1,
    "moveDistance": 4,
    "x": 2635,
    "y": 9576,
    "height": 2
  },
  {
    "id": "NpcId.FIRE_GIANT_86",
    "direction": 1,
    "moveDistance": 4,
    "x": 2630,
    "y": 9581,
    "height": 2
  },
  {
    "id": "NpcId.FIRE_GIANT_86",
    "direction": 1,
    "moveDistance": 4,
    "x": 2634,
    "y": 9586,
    "height": 2
  },
  {
    "id": "NpcId.FIRE_GIANT_86",
    "direction": 1,
    "moveDistance": 4,
    "x": 2634,
    "y": 9593,
    "height": 2
  },
  {
    "id": "NpcId.WILD_DOG_63",
    "direction": 1,
    "moveDistance": 4,
    "x": 2641,
    "y": 9594,
    "height": 2
  },
  {
    "id": "NpcId.FIRE_GIANT_86",
    "direction": 1,
    "moveDistance": 4,
    "x": 2651,
    "y": 9503
  },
  {
    "id": "NpcId.FIRE_GIANT_86",
    "direction": 1,
    "moveDistance": 4,
    "x": 2643,
    "y": 9492
  },
  {
    "id": "NpcId.FIRE_GIANT_86",
    "direction": 1,
    "moveDistance": 4,
    "x": 2646,
    "y": 9485
  },
  {
    "id": "NpcId.FIRE_GIANT_86",
    "direction": 1,
    "moveDistance": 4,
    "x": 2654,
    "y": 9488
  },
  {
    "id": "NpcId.FIRE_GIANT_86",
    "direction": 1,
    "moveDistance": 4,
    "x": 2656,
    "y": 9481
  },
  {
    "id": "NpcId.FIRE_GIANT_86",
    "direction": 1,
    "moveDistance": 4,
    "x": 2666,
    "y": 9483
  },
  {
    "id": "NpcId.FIRE_GIANT_86",
    "direction": 1,
    "moveDistance": 4,
    "x": 2668,
    "y": 9496
  },
  {
    "id": "NpcId.FIRE_GIANT_86",
    "direction": 1,
    "moveDistance": 4,
    "x": 2662,
    "y": 9494
  },
  {
    "id": "NpcId.FIRE_GIANT_86",
    "direction": 1,
    "moveDistance": 4,
    "x": 2658,
    "y": 9500
  },
  {
    "id": "NpcId.FIRE_GIANT_86",
    "direction": 1,
    "moveDistance": 4,
    "x": 2665,
    "y": 9504
  },
  {
    "id": "NpcId.RED_DRAGON_152",
    "direction": 1,
    "moveDistance": 4,
    "x": 2696,
    "y": 9506
  },
  {
    "id": "NpcId.RED_DRAGON_152",
    "direction": 1,
    "moveDistance": 4,
    "x": 2710,
    "y": 9502
  },
  {
    "id": "NpcId.RED_DRAGON_152",
    "direction": 1,
    "moveDistance": 4,
    "x": 2704,
    "y": 9518
  },
  {
    "id": "NpcId.RED_DRAGON_152",
    "direction": 1,
    "moveDistance": 4,
    "x": 2726,
    "y": 9514
  },
  {
    "id": "NpcId.RED_DRAGON_152",
    "direction": 1,
    "moveDistance": 4,
    "x": 2716,
    "y": 9522
  },
  {
    "id": "NpcId.RED_DRAGON_152",
    "direction": 1,
    "moveDistance": 4,
    "x": 2705,
    "y": 9537
  },
  {
    "id": "NpcId.RED_DRAGON_152",
    "direction": 1,
    "moveDistance": 4,
    "x": 2711,
    "y": 9547
  },
  {
    "id": "NpcId.BABY_RED_DRAGON_65",
    "direction": 1,
    "moveDistance": 4,
    "x": 2697,
    "y": 9514
  },
  {
    "id": "NpcId.BABY_RED_DRAGON_65",
    "direction": 1,
    "moveDistance": 4,
    "x": 2705,
    "y": 9507
  },
  {
    "id": "NpcId.BABY_RED_DRAGON_65",
    "direction": 1,
    "moveDistance": 4,
    "x": 2709,
    "y": 9516
  },
  {
    "id": "NpcId.BABY_RED_DRAGON_65",
    "direction": 1,
    "moveDistance": 4,
    "x": 2723,
    "y": 9520
  },
  {
    "id": "NpcId.BABY_RED_DRAGON_65",
    "direction": 1,
    "moveDistance": 4,
    "x": 2720,
    "y": 9535
  },
  {
    "id": "NpcId.BABY_RED_DRAGON_65",
    "direction": 1,
    "moveDistance": 4,
    "x": 2702,
    "y": 9547
  },
  {
    "id": "NpcId.WILD_DOG_63",
    "direction": 1,
    "moveDistance": 4,
    "x": 2686,
    "y": 9476
  },
  {
    "id": "NpcId.BLACK_DEMON_172",
    "direction": 1,
    "moveDistance": 4,
    "x": 2700,
    "y": 9489
  },
  {
    "id": "NpcId.BLACK_DEMON_172",
    "direction": 1,
    "moveDistance": 4,
    "x": 2703,
    "y": 9482
  },
  {
    "id": "NpcId.BLACK_DEMON_172",
    "direction": 1,
    "moveDistance": 4,
    "x": 2710,
    "y": 9479
  },
  {
    "id": "NpcId.BLACK_DEMON_172",
    "direction": 1,
    "moveDistance": 4,
    "x": 2709,
    "y": 9487
  },
  {
    "id": "NpcId.BLACK_DEMON_172",
    "direction": 1,
    "moveDistance": 4,
    "x": 2718,
    "y": 9484
  },
  {
    "id": "NpcId.BRONZE_DRAGON_131",
    "direction": 1,
    "moveDistance": 4,
    "x": 2732,
    "y": 9481
  },
  {
    "id": "NpcId.BRONZE_DRAGON_131",
    "direction": 1,
    "moveDistance": 4,
    "x": 2728,
    "y": 9488
  },
  {
    "id": "NpcId.BRONZE_DRAGON_131",
    "direction": 1,
    "moveDistance": 4,
    "x": 2741,
    "y": 9486
  },
  {
    "id": "NpcId.BRONZE_DRAGON_131",
    "direction": 1,
    "moveDistance": 4,
    "x": 2736,
    "y": 9493
  },
  {
    "id": "NpcId.WILD_DOG_63",
    "direction": 1,
    "moveDistance": 4,
    "x": 2742,
    "y": 9503
  },
  {
    "id": "NpcId.WILD_DOG_63",
    "direction": 1,
    "moveDistance": 4,
    "x": 2740,
    "y": 9508
  },
  {
    "id": "NpcId.STEEL_DRAGON_246_274",
    "direction": 1,
    "moveDistance": 4,
    "x": 2718,
    "y": 9448
  },
  {
    "id": "NpcId.STEEL_DRAGON_246_274",
    "direction": 1,
    "moveDistance": 4,
    "x": 2728,
    "y": 9443
  },
  {
    "id": "NpcId.STEEL_DRAGON_246_274",
    "direction": 1,
    "moveDistance": 4,
    "x": 2716,
    "y": 9436
  },
  {
    "id": "NpcId.STEEL_DRAGON_246_274",
    "direction": 1,
    "moveDistance": 4,
    "x": 2729,
    "y": 9433
  },
  {
    "id": "NpcId.STEEL_DRAGON_246_274",
    "direction": 1,
    "moveDistance": 4,
    "x": 2721,
    "y": 9428
  },
  {
    "id": "NpcId.STEEL_DRAGON_246_274",
    "direction": 1,
    "moveDistance": 4,
    "x": 2729,
    "y": 9455
  },
  {
    "id": "NpcId.IRON_DRAGON_189",
    "direction": 1,
    "moveDistance": 4,
    "x": 2713,
    "y": 9458
  },
  {
    "id": "NpcId.IRON_DRAGON_189",
    "direction": 1,
    "moveDistance": 4,
    "x": 2704,
    "y": 9450
  },
  {
    "id": "NpcId.IRON_DRAGON_189",
    "direction": 1,
    "moveDistance": 4,
    "x": 2704,
    "y": 9436
  },
  {
    "id": "NpcId.IRON_DRAGON_189",
    "direction": 1,
    "moveDistance": 4,
    "x": 2706,
    "y": 9424
  },
  {
    "id": "NpcId.IRON_DRAGON_189",
    "direction": 1,
    "moveDistance": 4,
    "x": 2718,
    "y": 9420
  },
  {
    "id": "NpcId.IRON_DRAGON_189",
    "direction": 1,
    "moveDistance": 444,
    "x": 2734,
    "y": 9420
  },
  {
    "id": "NpcId.IRON_DRAGON_189",
    "direction": 1,
    "moveDistance": 4,
    "x": 2740,
    "y": 9432
  },
  {
    "id": "NpcId.IRON_DRAGON_189",
    "direction": 1,
    "moveDistance": 4,
    "x": 2739,
    "y": 9451
  },
  {
    "id": "NpcId.IRON_DRAGON_189",
    "direction": 1,
    "moveDistance": 4,
    "x": 2711,
    "y": 9443
  },
  {
    "id": "NpcId.IRON_DRAGON_189",
    "direction": 1,
    "moveDistance": 4,
    "x": 2741,
    "y": 9443
  },
  {
    "id": "NpcId.IRON_DRAGON_189",
    "direction": 1,
    "moveDistance": 4,
    "x": 2739,
    "y": 9462
  },
  {
    "id": "NpcId.STEEL_DRAGON_246_274",
    "direction": 1,
    "moveDistance": 4,
    "x": 2668,
    "y": 9418
  },
  {
    "id": "NpcId.STEEL_DRAGON_246_274",
    "direction": 1,
    "moveDistance": 4,
    "x": 2656,
    "y": 9419
  },
  {
    "id": "NpcId.STEEL_DRAGON_246_274",
    "direction": 1,
    "moveDistance": 4,
    "x": 2656,
    "y": 9427
  },
  {
    "id": "NpcId.STEEL_DRAGON_246_274",
    "direction": 1,
    "moveDistance": 4,
    "x": 2648,
    "y": 9422
  },
  {
    "id": "NpcId.STEEL_DRAGON_246_274",
    "direction": 1,
    "moveDistance": 4,
    "x": 2647,
    "y": 9431
  },
  {
    "id": "NpcId.STEEL_DRAGON_246_274",
    "direction": 1,
    "moveDistance": 4,
    "x": 2633,
    "y": 9420
  },
  {
    "id": "NpcId.STEEL_DRAGON_246_274",
    "direction": 1,
    "moveDistance": 4,
    "x": 2639,
    "y": 9418
  },
  {
    "id": "NpcId.STEEL_DRAGON_246_274",
    "direction": 1,
    "moveDistance": 4,
    "x": 2637,
    "y": 9429
  },
  {
    "id": "NpcId.STEEL_DRAGON_246_274",
    "direction": 1,
    "moveDistance": 4,
    "x": 2639,
    "y": 9437
  },
  {
    "id": "NpcId.STEEL_DRAGON_246_274",
    "direction": 1,
    "moveDistance": 4,
    "x": 2670,
    "y": 9426
  },
  {
    "id": "NpcId.BRONZE_DRAGON_131",
    "direction": 1,
    "moveDistance": 4,
    "x": 2641,
    "y": 9445
  },
  {
    "id": "NpcId.BRONZE_DRAGON_131",
    "direction": 1,
    "moveDistance": 4,
    "x": 2636,
    "y": 9450
  },
  {
    "id": "NpcId.BRONZE_DRAGON_131",
    "direction": 1,
    "moveDistance": 4,
    "x": 2648,
    "y": 9451
  },
  {
    "id": "NpcId.BRONZE_DRAGON_131",
    "direction": 1,
    "moveDistance": 4,
    "x": 2634,
    "y": 9458
  },
  {
    "id": "NpcId.BRONZE_DRAGON_131",
    "direction": 1,
    "moveDistance": 4,
    "x": 2642,
    "y": 9454
  },
  {
    "id": "NpcId.IRON_DRAGON_189",
    "direction": 1,
    "moveDistance": 4,
    "x": 2675,
    "y": 9440
  },
  {
    "id": "NpcId.IRON_DRAGON_189",
    "direction": 1,
    "moveDistance": 4,
    "x": 2669,
    "y": 9445
  },
  {
    "id": "NpcId.IRON_DRAGON_189",
    "direction": 1,
    "moveDistance": 4,
    "x": 2667,
    "y": 9452
  },
  {
    "id": "NpcId.IRON_DRAGON_189",
    "direction": 1,
    "moveDistance": 4,
    "x": 2659,
    "y": 9454
  },
  {
    "id": "NpcId.IRON_DRAGON_189",
    "direction": 1,
    "moveDistance": 4,
    "x": 2664,
    "y": 9460
  },
  {
    "id": "NpcId.IRON_DRAGON_189",
    "direction": 1,
    "moveDistance": 4,
    "x": 2676,
    "y": 9451
  },
  {
    "id": "NpcId.IRON_DRAGON_189",
    "direction": 1,
    "moveDistance": 4,
    "x": 2672,
    "y": 9459
  }
]
